config.py
draft_generator.py
opendraft/__init__.py
opendraft/cli.py
opendraft/verify.py
opendraft/version.py
utils/__init__.py
utils/abstract_generator.py
utils/agent_runner.py
utils/api_tier_detector.py
utils/backpressure.py
utils/citation_compiler.py
utils/citation_database.py
utils/citation_quality_filter.py
utils/citation_validator.py
utils/deduplicate_citations.py
utils/deep_research.py
utils/docx_post_processor.py
utils/error_mapper.py
utils/exceptions.py
utils/export_professional.py
utils/fallback_services.py
utils/logging_config.py
utils/output_validators.py
utils/progress_tracker.py
utils/retry.py
utils/scrape_citation_metadata.py
utils/scrape_citation_titles.py
utils/structured_logger.py
utils/text_utils.py
utils/url_context_fallback.py
utils/web_search_fallback.py
utils/api_citations/__init__.py
utils/api_citations/base.py
utils/api_citations/crossref.py
utils/api_citations/dataforseo_client.py
utils/api_citations/gemini_grounded.py
utils/api_citations/orchestrator.py
utils/api_citations/query_router.py
utils/api_citations/semantic_scholar.py
utils/pdf_engines/__init__.py
utils/pdf_engines/base.py
utils/pdf_engines/factory.py
utils/pdf_engines/libreoffice_engine.py
utils/pdf_engines/pandoc_engine.py
utils/pdf_engines/weasyprint_engine.py
opendraft-1.6.22.dist-info/METADATA
opendraft-1.6.22.dist-info/WHEEL
opendraft-1.6.22.dist-info/entry_points.txt
opendraft-1.6.22.dist-info/top_level.txt
opendraft-1.6.22.dist-info/RECORD
