Metadata-Version: 2.4
Name: opendraft
Version: 1.6.22
Summary: Generate master-level research papers with real citations in minutes
Author: Federico De Ponte
Maintainer: Federico De Ponte
License: MIT
Project-URL: Homepage, https://opendraft.xyz
Project-URL: Documentation, https://github.com/federicodeponte/opendraft/tree/main/docs
Project-URL: Repository, https://github.com/federicodeponte/opendraft
Project-URL: Changelog, https://github.com/federicodeponte/opendraft/blob/main/CHANGELOG.md
Project-URL: Bug Tracker, https://github.com/federicodeponte/opendraft/issues
Keywords: academic-writing,draft,ai,research,citation-management,llm,pdf-generation,scholarly
Classifier: Development Status :: 4 - Beta
Classifier: Intended Audience :: Science/Research
Classifier: Intended Audience :: Education
Classifier: License :: OSI Approved :: MIT License
Classifier: Programming Language :: Python :: 3
Classifier: Programming Language :: Python :: 3.10
Classifier: Programming Language :: Python :: 3.11
Classifier: Programming Language :: Python :: 3.12
Classifier: Topic :: Scientific/Engineering
Classifier: Topic :: Text Processing :: Markup :: Markdown
Classifier: Topic :: Text Processing :: Markup :: LaTeX
Requires-Python: >=3.10
Requires-Dist: anthropic>=0.20.0
Requires-Dist: openai>=1.0.0
Requires-Dist: google-generativeai>=0.8.0
Requires-Dist: pybtex>=0.24.0
Requires-Dist: citeproc-py>=0.6.0
Requires-Dist: PyYAML>=6.0.0
Requires-Dist: markdown>=3.5.0
Requires-Dist: weasyprint>=60.0
Requires-Dist: python-docx>=1.0.0
Requires-Dist: requests>=2.31.0
Requires-Dist: beautifulsoup4>=4.12.0
Requires-Dist: lxml>=4.9.0
Requires-Dist: python-dotenv>=1.0.0
Requires-Dist: rich>=13.0.0
Requires-Dist: psutil>=5.9.0
Provides-Extra: dev
Requires-Dist: pytest>=7.4.0; extra == "dev"
Requires-Dist: pytest-cov>=4.1.0; extra == "dev"
Requires-Dist: black>=23.0.0; extra == "dev"
Requires-Dist: flake8>=6.0.0; extra == "dev"
Requires-Dist: mypy>=1.5.0; extra == "dev"
Requires-Dist: isort>=5.12.0; extra == "dev"
Provides-Extra: docker
Requires-Dist: streamlit>=1.28.0; extra == "docker"
Provides-Extra: all
Requires-Dist: opendraft[dev,docker]; extra == "all"
